{"race": "케이오카쿠 1경주", "date": "2026-07-19", "raceKey": "케이오카쿠 1경주", "snapshots": [{"time": "20:40:41", "minutes_before": 9, "mb_signed": 9, "after_close": false, "deadline_corrected": false, "baseline_reset": false, "next_race_blocked": false, "signal_horse": null, "signal_reason": null, "quinella": {"1+2": 6.2, "1+3": 1.5, "2+3": 9.6, "1+4": 19.6, "2+4": 29.0, "3+4": 18.1, "1+5": 19.3, "2+5": 45.9, "3+5": 40.5, "4+5": 26.0, "1+6": 37.1, "2+6": 37.9, "3+6": 45.9, "4+6": 109.0, "5+6": 145.3, "1+7": 33.5, "2+7": 79.2, "3+7": 67.0, "4+7": 174.4, "5+7": 218.0, "6+7": 124.6}, "exacta": {"1+2": 15.1, "1+3": 4.6, "1+4": 79.7, "1+5": 79.7, "1+6": 159.4, "1+7": 358.7, "2+1": 9.8, "2+3": 19.0, "2+4": 110.3, "2+5": 70.0, "2+6": 61.0, "2+7": 358.7, "3+1": 1.9, "3+2": 22.9, "3+4": 106.3, "3+5": 95.6, "3+6": 151.0, "3+7": 318.9, "4+1": 32.2, "4+2": 46.2, "4+3": 71.7, "4+5": 47.0, "4+6": 318.9, "4+7": 478.3, "5+1": 71.7, "5+2": 59.7, "5+3": 143.5, "5+4": 77.5, "5+6": 410.0, "5+7": 956.7, "6+1": 79.7, "6+2": 31.1, "6+3": 89.6, "6+4": 318.9, "6+5": 287.0, "6+7": 478.3, "7+1": 151.0, "7+2": 124.7, "7+3": 89.6, "7+4": 318.9, "7+5": 151.0, "7+6": 410.0}, "win": {}, "anomalies": [], "t": 1784461241.1998677}, {"time": "20:42:27", "minutes_before": 8, "mb_signed": 8, "after_close": false, "deadline_corrected": false, "baseline_reset": false, "next_race_blocked": false, "signal_horse": null, "signal_reason": null, "quinella": {"1+2": 6.5, "1+3": 1.5, "2+3": 9.6, "1+4": 19.0, "2+4": 28.6, "3+4": 20.4, "1+5": 19.9, "2+5": 42.1, "3+5": 36.4, "4+5": 27.9, "1+6": 35.2, "2+6": 32.6, "3+6": 41.3, "4+6": 119.5, "5+6": 126.5, "1+7": 32.6, "2+7": 86.0, "3+7": 58.1, "4+7": 215.1, "5+7": 179.3, "6+7": 143.4}, "exacta": {"1+2": 16.1, "1+3": 3.6, "1+4": 88.5, "1+5": 68.6, "1+6": 189.6, "1+7": 398.2, "2+1": 11.6, "2+3": 19.3, "2+4": 117.1, "2+5": 64.2, "2+6": 78.0, "2+7": 398.2, "3+1": 2.0, "3+2": 24.4, "3+4": 120.6, "3+5": 92.6, "3+6": 181.0, "3+7": 331.8, "4+1": 36.2, "4+2": 50.4, "4+3": 84.7, "4+5": 51.0, "4+6": 306.3, "4+7": 568.9, "5+1": 65.2, "5+2": 61.2, "5+3": 132.7, "5+4": 73.7, "5+6": 442.5, "5+7": 796.5, "6+1": 84.7, "6+2": 31.6, "6+3": 107.6, "6+4": 306.3, "6+5": 306.3, "6+7": 497.8, "7+1": 128.4, "7+2": 128.4, "7+3": 92.6, "7+4": 331.8, "7+5": 173.1, "7+6": 442.5}, "win": {}, "anomalies": [], "t": 1784461347.1174533}, {"time": "20:43:28", "minutes_before": 7, "mb_signed": 7, "after_close": false, "deadline_corrected": false, "baseline_reset": false, "next_race_blocked": false, "signal_horse": null, "signal_reason": null, "quinella": {"1+2": 6.5, "1+3": 1.5, "2+3": 9.6, "1+4": 19.0, "2+4": 28.6, "3+4": 20.4, "1+5": 19.9, "2+5": 42.1, "3+5": 36.4, "4+5": 27.9, "1+6": 35.2, "2+6": 32.6, "3+6": 41.3, "4+6": 119.5, "5+6": 126.5, "1+7": 32.6, "2+7": 86.0, "3+7": 58.1, "4+7": 215.1, "5+7": 179.3, "6+7": 143.4}, "exacta": {"1+2": 19.2, "1+3": 4.3, "1+4": 102.7, "1+5": 82.8, "1+6": 223.3, "1+7": 466.9, "2+1": 13.1, "2+3": 23.1, "2+4": 128.4, "2+5": 76.6, "2+6": 95.1, "2+7": 466.9, "3+1": 1.6, "3+2": 28.6, "3+4": 138.8, "3+5": 109.2, "3+6": 214.0, "3+7": 395.1, "4+1": 40.4, "4+2": 59.7, "4+3": 87.0, "4+5": 61.8, "4+6": 342.4, "4+7": 642.0, "5+1": 72.3, "5+2": 72.3, "5+3": 135.1, "5+4": 88.5, "5+6": 513.6, "5+7": 856.1, "6+1": 90.1, "6+2": 38.6, "6+3": 114.1, "6+4": 366.9, "6+5": 366.9, "6+7": 570.7, "7+1": 138.8, "7+2": 155.6, "7+3": 107.0, "7+4": 366.9, "7+5": 214.0, "7+6": 513.6}, "win": {}, "anomalies": [], "t": 1784461408.6377177}, {"time": "20:44:27", "minutes_before": 6, "mb_signed": 6, "after_close": false, "deadline_corrected": false, "baseline_reset": false, "next_race_blocked": false, "signal_horse": 2, "signal_reason": "2번 집중급락(평균 -10.0%)", "quinella": {"1+2": 6.5, "1+3": 1.5, "2+3": 9.1, "1+4": 18.4, "2+4": 25.7, "3+4": 20.4, "1+5": 20.9, "2+5": 41.5, "3+5": 38.1, "4+5": 28.1, "1+6": 36.9, "2+6": 29.2, "3+6": 44.6, "4+6": 118.3, "5+6": 139.2, "1+7": 35.3, "2+7": 91.0, "3+7": 60.7, "4+7": 215.2, "5+7": 197.3, "6+7": 157.8}, "exacta": {"1+2": 19.6, "1+3": 4.2, "1+4": 107.6, "1+5": 62.0, "1+6": 248.0, "1+7": 518.5, "2+1": 12.0, "2+3": 22.9, "2+4": 135.8, "2+5": 55.9, "2+6": 95.0, "2+7": 518.5, "3+1": 1.7, "3+2": 27.9, "3+4": 146.2, "3+5": 80.3, "3+6": 190.1, "3+7": 438.8, "4+1": 39.6, "4+2": 58.2, "4+3": 80.3, "4+5": 45.2, "4+6": 380.3, "4+7": 713.0, "5+1": 69.5, "5+2": 67.9, "5+3": 114.0, "5+4": 86.4, "5+6": 570.4, "5+7": 950.7, "6+1": 89.1, "6+2": 38.5, "6+3": 98.3, "6+4": 407.4, "6+5": 356.5, "6+7": 633.8, "7+1": 142.6, "7+2": 154.1, "7+3": 95.0, "7+4": 407.4, "7+5": 237.6, "7+6": 570.4}, "win": {}, "anomalies": [], "t": 1784461467.780257}, {"time": "20:45:26", "minutes_before": 5, "mb_signed": 5, "after_close": false, "deadline_corrected": false, "baseline_reset": false, "next_race_blocked": false, "signal_horse": null, "signal_reason": null, "quinella": {"1+2": 6.6, "1+3": 1.4, "2+3": 9.5, "1+4": 21.3, "2+4": 33.1, "3+4": 24.4, "1+5": 21.7, "2+5": 44.7, "3+5": 40.2, "4+5": 31.1, "1+6": 40.7, "2+6": 30.5, "3+6": 54.8, "4+6": 144.4, "5+6": 144.4, "1+7": 42.3, "2+7": 113.5, "3+7": 73.9, "4+7": 288.9, "5+7": 244.5, "6+7": 186.9}, "exacta": {"1+2": 19.6, "1+3": 4.2, "1+4": 107.6, "1+5": 62.0, "1+6": 248.0, "1+7": 518.5, "2+1": 12.0, "2+3": 22.9, "2+4": 135.8, "2+5": 55.9, "2+6": 95.0, "2+7": 518.5, "3+1": 1.7, "3+2": 27.9, "3+4": 146.2, "3+5": 80.3, "3+6": 190.1, "3+7": 438.8, "4+1": 39.6, "4+2": 58.2, "4+3": 80.3, "4+5": 45.2, "4+6": 380.3, "4+7": 713.0, "5+1": 69.5, "5+2": 67.9, "5+3": 114.0, "5+4": 86.4, "5+6": 570.4, "5+7": 950.7, "6+1": 89.1, "6+2": 38.5, "6+3": 98.3, "6+4": 407.4, "6+5": 356.5, "6+7": 633.8, "7+1": 142.6, "7+2": 154.1, "7+3": 95.0, "7+4": 407.4, "7+5": 237.6, "7+6": 570.4}, "win": {}, "anomalies": [], "t": 1784461526.607156}, {"time": "20:46:28", "minutes_before": 4, "mb_signed": 4, "after_close": false, "deadline_corrected": false, "baseline_reset": false, "next_race_blocked": false, "signal_horse": 5, "signal_reason": "5번 집중급락(평균 -16.0%)", "quinella": {"1+2": 6.5, "1+3": 1.4, "2+3": 10.1, "1+4": 22.8, "2+4": 35.1, "3+4": 26.2, "1+5": 22.0, "2+5": 37.6, "3+5": 42.4, "4+5": 30.2, "1+6": 51.5, "2+6": 26.2, "3+6": 65.5, "4+6": 154.5, "5+6": 173.0, "1+7": 56.9, "2+7": 135.2, "3+7": 94.0, "4+7": 309.0, "5+7": 332.8, "6+7": 254.5}, "exacta": {"1+2": 17.2, "1+3": 3.8, "1+4": 125.7, "1+5": 48.4, "1+6": 277.6, "1+7": 619.2, "2+1": 11.6, "2+3": 21.5, "2+4": 164.2, "2+5": 48.7, "2+6": 111.8, "2+7": 731.8, "3+1": 1.9, "3+2": 25.7, "3+4": 167.7, "3+5": 66.5, "3+6": 236.7, "3+7": 536.7, "4+1": 36.1, "4+2": 59.1, "4+3": 70.0, "4+5": 39.2, "4+6": 447.2, "4+7": 1006.3, "5+1": 67.0, "5+2": 68.2, "5+3": 103.2, "5+4": 88.4, "5+6": 575.0, "5+7": 1006.3, "6+1": 87.5, "6+2": 33.2, "6+3": 93.6, "6+4": 536.7, "6+5": 423.7, "6+7": 731.8, "7+1": 129.8, "7+2": 143.7, "7+3": 89.4, "7+4": 503.1, "7+5": 277.6, "7+6": 536.7}, "win": {}, "anomalies": [], "t": 1784461588.8444653}, {"time": "20:47:37", "minutes_before": 2, "mb_signed": 2, "after_close": false, "deadline_corrected": false, "baseline_reset": false, "next_race_blocked": false, "signal_horse": 4, "signal_reason": "4번 집중급락(평균 -47.0%)", "quinella": {"1+2": 7.1, "1+3": 1.5, "2+3": 10.7, "1+4": 24.0, "2+4": 38.4, "3+4": 28.7, "1+5": 12.3, "2+5": 22.5, "3+5": 37.3, "4+5": 16.1, "1+6": 56.8, "2+6": 21.6, "3+6": 72.9, "4+6": 162.9, "5+6": 181.0, "1+7": 64.3, "2+7": 152.7, "3+7": 106.2, "4+7": 305.5, "5+7": 376.0, "6+7": 257.2}, "exacta": {"1+2": 16.8, "1+3": 4.1, "1+4": 123.0, "1+5": 25.7, "1+6": 293.7, "1+7": 650.4, "2+1": 12.8, "2+3": 23.6, "2+4": 171.8, "2+5": 34.2, "2+6": 118.2, "2+7": 758.8, "3+1": 2.1, "3+2": 26.8, "3+4": 185.8, "3+5": 51.4, "3+6": 260.1, "3+7": 607.1, "4+1": 34.6, "4+2": 56.9, "4+3": 77.1, "4+5": 19.5, "4+6": 505.9, "4+7": 1011.8, "5+1": 29.0, "5+2": 41.0, "5+3": 105.8, "5+4": 68.9, "5+6": 607.1, "5+7": 1011.8, "6+1": 97.9, "6+2": 28.0, "6+3": 105.8, "6+4": 569.1, "6+5": 433.6, "6+7": 827.8, "7+1": 146.8, "7+2": 135.9, "7+3": 101.1, "7+4": 479.2, "7+5": 275.9, "7+6": 607.1}, "win": {}, "anomalies": ["급락감지: 1+5 -44%", "급락감지: 2+5 -40%", "급락감지: 4+5 -47%"], "t": 1784461657.7519777}, {"time": "20:48:36", "minutes_before": 1, "mb_signed": 1, "after_close": false, "deadline_corrected": false, "baseline_reset": false, "next_race_blocked": false, "signal_horse": 2, "signal_reason": "2번 집중급락(평균 -16.0%)", "quinella": {"1+2": 7.4, "1+3": 1.5, "2+3": 11.0, "1+4": 24.9, "2+4": 39.8, "3+4": 29.7, "1+5": 10.5, "2+5": 18.8, "3+5": 33.7, "4+5": 13.5, "1+6": 57.5, "2+6": 22.4, "3+6": 75.5, "4+6": 168.8, "5+6": 187.5, "1+7": 66.6, "2+7": 158.2, "3+7": 110.0, "4+7": 316.5, "5+7": 389.5, "6+7": 266.5}, "exacta": {"1+2": 17.5, "1+3": 4.2, "1+4": 127.2, "1+5": 23.0, "1+6": 293.0, "1+7": 568.8, "2+1": 11.8, "2+3": 24.6, "2+4": 175.8, "2+5": 33.3, "2+6": 122.4, "2+7": 743.8, "3+1": 2.3, "3+2": 27.9, "3+4": 193.3, "3+5": 49.3, "3+6": 235.8, "3+7": 604.3, "4+1": 35.5, "4+2": 54.3, "4+3": 77.9, "4+5": 16.7, "4+6": 402.9, "4+7": 966.9, "5+1": 21.3, "5+2": 35.8, "5+3": 89.5, "5+4": 63.2, "5+6": 604.3, "5+7": 966.9, "6+1": 95.7, "6+2": 29.2, "6+3": 103.9, "6+4": 568.8, "6+5": 371.9, "6+7": 805.8, "7+1": 153.4, "7+2": 140.1, "7+3": 106.2, "7+4": 483.4, "7+5": 276.2, "7+6": 604.3}, "win": {}, "anomalies": [], "t": 1784461716.8476248}, {"time": "20:49:37", "minutes_before": 0, "mb_signed": 0, "after_close": false, "deadline_corrected": false, "baseline_reset": false, "next_race_blocked": false, "signal_horse": null, "signal_reason": null, "quinella": {"1+2": 7.4, "1+3": 1.5, "2+3": 11.0, "1+4": 24.9, "2+4": 39.8, "3+4": 29.7, "1+5": 10.5, "2+5": 18.8, "3+5": 33.7, "4+5": 13.5, "1+6": 57.5, "2+6": 22.4, "3+6": 75.5, "4+6": 168.8, "5+6": 187.5, "1+7": 66.6, "2+7": 158.2, "3+7": 110.0, "4+7": 316.5, "5+7": 389.5, "6+7": 266.5}, "exacta": {"1+2": 17.5, "1+3": 4.2, "1+4": 127.2, "1+5": 23.0, "1+6": 293.0, "1+7": 568.8, "2+1": 11.8, "2+3": 24.6, "2+4": 175.8, "2+5": 33.3, "2+6": 122.4, "2+7": 743.8, "3+1": 2.3, "3+2": 27.9, "3+4": 193.3, "3+5": 49.3, "3+6": 235.8, "3+7": 604.3, "4+1": 35.5, "4+2": 54.3, "4+3": 77.9, "4+5": 16.7, "4+6": 402.9, "4+7": 966.9, "5+1": 21.3, "5+2": 35.8, "5+3": 89.5, "5+4": 63.2, "5+6": 604.3, "5+7": 966.9, "6+1": 95.7, "6+2": 29.2, "6+3": 103.9, "6+4": 568.8, "6+5": 371.9, "6+7": 805.8, "7+1": 153.4, "7+2": 140.1, "7+3": 106.2, "7+4": 483.4, "7+5": 276.2, "7+6": 604.3}, "win": {}, "anomalies": [], "t": 1784461777.901838}, {"time": "20:50:38", "minutes_before": null, "mb_signed": -1, "after_close": true, "deadline_corrected": false, "baseline_reset": false, "next_race_blocked": false, "signal_horse": null, "signal_reason": null, "quinella": {"1+2": 7.4, "1+3": 1.5, "2+3": 11.0, "1+4": 24.9, "2+4": 39.8, "3+4": 29.7, "1+5": 10.5, "2+5": 18.8, "3+5": 33.7, "4+5": 13.5, "1+6": 57.5, "2+6": 22.4, "3+6": 75.5, "4+6": 168.8, "5+6": 187.5, "1+7": 66.6, "2+7": 158.2, "3+7": 110.0, "4+7": 316.5, "5+7": 389.5, "6+7": 266.5}, "exacta": {"1+2": 17.5, "1+3": 4.2, "1+4": 127.2, "1+5": 23.0, "1+6": 293.0, "1+7": 568.8, "2+1": 11.8, "2+3": 24.6, "2+4": 175.8, "2+5": 33.3, "2+6": 122.4, "2+7": 743.8, "3+1": 2.3, "3+2": 27.9, "3+4": 193.3, "3+5": 49.3, "3+6": 235.8, "3+7": 604.3, "4+1": 35.5, "4+2": 54.3, "4+3": 77.9, "4+5": 16.7, "4+6": 402.9, "4+7": 966.9, "5+1": 21.3, "5+2": 35.8, "5+3": 89.5, "5+4": 63.2, "5+6": 604.3, "5+7": 966.9, "6+1": 95.7, "6+2": 29.2, "6+3": 103.9, "6+4": 568.8, "6+5": 371.9, "6+7": 805.8, "7+1": 153.4, "7+2": 140.1, "7+3": 106.2, "7+4": 483.4, "7+5": 276.2, "7+6": 604.3}, "win": {}, "anomalies": [], "t": 1784461838.0100398}, {"time": "20:51:46", "minutes_before": null, "mb_signed": -2, "after_close": true, "deadline_corrected": false, "baseline_reset": false, "next_race_blocked": false, "signal_horse": null, "signal_reason": null, "quinella": {"1+2": 7.4, "1+3": 1.5, "2+3": 11.0, "1+4": 24.9, "2+4": 39.8, "3+4": 29.7, "1+5": 10.5, "2+5": 18.8, "3+5": 33.7, "4+5": 13.5, "1+6": 57.5, "2+6": 22.4, "3+6": 75.5, "4+6": 168.8, "5+6": 187.5, "1+7": 66.6, "2+7": 158.2, "3+7": 110.0, "4+7": 316.5, "5+7": 389.5, "6+7": 266.5}, "exacta": {"1+2": 17.5, "1+3": 4.2, "1+4": 127.2, "1+5": 23.0, "1+6": 293.0, "1+7": 568.8, "2+1": 11.8, "2+3": 24.6, "2+4": 175.8, "2+5": 33.3, "2+6": 122.4, "2+7": 743.8, "3+1": 2.3, "3+2": 27.9, "3+4": 193.3, "3+5": 49.3, "3+6": 235.8, "3+7": 604.3, "4+1": 35.5, "4+2": 54.3, "4+3": 77.9, "4+5": 16.7, "4+6": 402.9, "4+7": 966.9, "5+1": 21.3, "5+2": 35.8, "5+3": 89.5, "5+4": 63.2, "5+6": 604.3, "5+7": 966.9, "6+1": 95.7, "6+2": 29.2, "6+3": 103.9, "6+4": 568.8, "6+5": 371.9, "6+7": 805.8, "7+1": 153.4, "7+2": 140.1, "7+3": 106.2, "7+4": 483.4, "7+5": 276.2, "7+6": 604.3}, "win": {}, "anomalies": [], "t": 1784461906.6470385}], "result": null, "archive_snapshots": [{"time": "20:40:41", "t": 1784461241.1998677, "minutes_before": 9, "mb_signed": 9, "after_close": false, "baseline_reset": false, "next_race_blocked": false, "quinella": {"1+2": 6.2, "1+3": 1.5, "2+3": 9.6, "1+4": 19.6, "2+4": 29.0, "3+4": 18.1, "1+5": 19.3, "2+5": 45.9, "3+5": 40.5, "4+5": 26.0, "1+6": 37.1, "2+6": 37.9, "3+6": 45.9, "4+6": 109.0, "5+6": 145.3, "1+7": 33.5, "2+7": 79.2, "3+7": 67.0, "4+7": 174.4, "5+7": 218.0, "6+7": 124.6}, "exacta": {"1+2": 15.1, "1+3": 4.6, "1+4": 79.7, "1+5": 79.7, "1+6": 159.4, "1+7": 358.7, "2+1": 9.8, "2+3": 19.0, "2+4": 110.3, "2+5": 70.0, "2+6": 61.0, "2+7": 358.7, "3+1": 1.9, "3+2": 22.9, "3+4": 106.3, "3+5": 95.6, "3+6": 151.0, "3+7": 318.9, "4+1": 32.2, "4+2": 46.2, "4+3": 71.7, "4+5": 47.0, "4+6": 318.9, "4+7": 478.3, "5+1": 71.7, "5+2": 59.7, "5+3": 143.5, "5+4": 77.5, "5+6": 410.0, "5+7": 956.7, "6+1": 79.7, "6+2": 31.1, "6+3": 89.6, "6+4": 318.9, "6+5": 287.0, "6+7": 478.3, "7+1": 151.0, "7+2": 124.7, "7+3": 89.6, "7+4": 318.9, "7+5": 151.0, "7+6": 410.0}, "win": {}, "anomalies": []}, {"time": "20:42:27", "t": 1784461347.1174533, "minutes_before": 8, "mb_signed": 8, "after_close": false, "baseline_reset": false, "next_race_blocked": false, "quinella": {"1+2": 6.5, "1+3": 1.5, "2+3": 9.6, "1+4": 19.0, "2+4": 28.6, "3+4": 20.4, "1+5": 19.9, "2+5": 42.1, "3+5": 36.4, "4+5": 27.9, "1+6": 35.2, "2+6": 32.6, "3+6": 41.3, "4+6": 119.5, "5+6": 126.5, "1+7": 32.6, "2+7": 86.0, "3+7": 58.1, "4+7": 215.1, "5+7": 179.3, "6+7": 143.4}, "exacta": {"1+2": 16.1, "1+3": 3.6, "1+4": 88.5, "1+5": 68.6, "1+6": 189.6, "1+7": 398.2, "2+1": 11.6, "2+3": 19.3, "2+4": 117.1, "2+5": 64.2, "2+6": 78.0, "2+7": 398.2, "3+1": 2.0, "3+2": 24.4, "3+4": 120.6, "3+5": 92.6, "3+6": 181.0, "3+7": 331.8, "4+1": 36.2, "4+2": 50.4, "4+3": 84.7, "4+5": 51.0, "4+6": 306.3, "4+7": 568.9, "5+1": 65.2, "5+2": 61.2, "5+3": 132.7, "5+4": 73.7, "5+6": 442.5, "5+7": 796.5, "6+1": 84.7, "6+2": 31.6, "6+3": 107.6, "6+4": 306.3, "6+5": 306.3, "6+7": 497.8, "7+1": 128.4, "7+2": 128.4, "7+3": 92.6, "7+4": 331.8, "7+5": 173.1, "7+6": 442.5}, "win": {}, "anomalies": []}, {"time": "20:43:28", "t": 1784461408.6377177, "minutes_before": 7, "mb_signed": 7, "after_close": false, "baseline_reset": false, "next_race_blocked": false, "quinella": {"1+2": 6.5, "1+3": 1.5, "2+3": 9.6, "1+4": 19.0, "2+4": 28.6, "3+4": 20.4, "1+5": 19.9, "2+5": 42.1, "3+5": 36.4, "4+5": 27.9, "1+6": 35.2, "2+6": 32.6, "3+6": 41.3, "4+6": 119.5, "5+6": 126.5, "1+7": 32.6, "2+7": 86.0, "3+7": 58.1, "4+7": 215.1, "5+7": 179.3, "6+7": 143.4}, "exacta": {"1+2": 19.2, "1+3": 4.3, "1+4": 102.7, "1+5": 82.8, "1+6": 223.3, "1+7": 466.9, "2+1": 13.1, "2+3": 23.1, "2+4": 128.4, "2+5": 76.6, "2+6": 95.1, "2+7": 466.9, "3+1": 1.6, "3+2": 28.6, "3+4": 138.8, "3+5": 109.2, "3+6": 214.0, "3+7": 395.1, "4+1": 40.4, "4+2": 59.7, "4+3": 87.0, "4+5": 61.8, "4+6": 342.4, "4+7": 642.0, "5+1": 72.3, "5+2": 72.3, "5+3": 135.1, "5+4": 88.5, "5+6": 513.6, "5+7": 856.1, "6+1": 90.1, "6+2": 38.6, "6+3": 114.1, "6+4": 366.9, "6+5": 366.9, "6+7": 570.7, "7+1": 138.8, "7+2": 155.6, "7+3": 107.0, "7+4": 366.9, "7+5": 214.0, "7+6": 513.6}, "win": {}, "anomalies": []}, {"time": "20:44:27", "t": 1784461467.780257, "minutes_before": 6, "mb_signed": 6, "after_close": false, "baseline_reset": false, "next_race_blocked": false, "quinella": {"1+2": 6.5, "1+3": 1.5, "2+3": 9.1, "1+4": 18.4, "2+4": 25.7, "3+4": 20.4, "1+5": 20.9, "2+5": 41.5, "3+5": 38.1, "4+5": 28.1, "1+6": 36.9, "2+6": 29.2, "3+6": 44.6, "4+6": 118.3, "5+6": 139.2, "1+7": 35.3, "2+7": 91.0, "3+7": 60.7, "4+7": 215.2, "5+7": 197.3, "6+7": 157.8}, "exacta": {"1+2": 19.6, "1+3": 4.2, "1+4": 107.6, "1+5": 62.0, "1+6": 248.0, "1+7": 518.5, "2+1": 12.0, "2+3": 22.9, "2+4": 135.8, "2+5": 55.9, "2+6": 95.0, "2+7": 518.5, "3+1": 1.7, "3+2": 27.9, "3+4": 146.2, "3+5": 80.3, "3+6": 190.1, "3+7": 438.8, "4+1": 39.6, "4+2": 58.2, "4+3": 80.3, "4+5": 45.2, "4+6": 380.3, "4+7": 713.0, "5+1": 69.5, "5+2": 67.9, "5+3": 114.0, "5+4": 86.4, "5+6": 570.4, "5+7": 950.7, "6+1": 89.1, "6+2": 38.5, "6+3": 98.3, "6+4": 407.4, "6+5": 356.5, "6+7": 633.8, "7+1": 142.6, "7+2": 154.1, "7+3": 95.0, "7+4": 407.4, "7+5": 237.6, "7+6": 570.4}, "win": {}, "anomalies": []}, {"time": "20:45:26", "t": 1784461526.607156, "minutes_before": 5, "mb_signed": 5, "after_close": false, "baseline_reset": false, "next_race_blocked": false, "quinella": {"1+2": 6.6, "1+3": 1.4, "2+3": 9.5, "1+4": 21.3, "2+4": 33.1, "3+4": 24.4, "1+5": 21.7, "2+5": 44.7, "3+5": 40.2, "4+5": 31.1, "1+6": 40.7, "2+6": 30.5, "3+6": 54.8, "4+6": 144.4, "5+6": 144.4, "1+7": 42.3, "2+7": 113.5, "3+7": 73.9, "4+7": 288.9, "5+7": 244.5, "6+7": 186.9}, "exacta": {"1+2": 19.6, "1+3": 4.2, "1+4": 107.6, "1+5": 62.0, "1+6": 248.0, "1+7": 518.5, "2+1": 12.0, "2+3": 22.9, "2+4": 135.8, "2+5": 55.9, "2+6": 95.0, "2+7": 518.5, "3+1": 1.7, "3+2": 27.9, "3+4": 146.2, "3+5": 80.3, "3+6": 190.1, "3+7": 438.8, "4+1": 39.6, "4+2": 58.2, "4+3": 80.3, "4+5": 45.2, "4+6": 380.3, "4+7": 713.0, "5+1": 69.5, "5+2": 67.9, "5+3": 114.0, "5+4": 86.4, "5+6": 570.4, "5+7": 950.7, "6+1": 89.1, "6+2": 38.5, "6+3": 98.3, "6+4": 407.4, "6+5": 356.5, "6+7": 633.8, "7+1": 142.6, "7+2": 154.1, "7+3": 95.0, "7+4": 407.4, "7+5": 237.6, "7+6": 570.4}, "win": {}, "anomalies": []}, {"time": "20:46:28", "t": 1784461588.8444653, "minutes_before": 4, "mb_signed": 4, "after_close": false, "baseline_reset": false, "next_race_blocked": false, "quinella": {"1+2": 6.5, "1+3": 1.4, "2+3": 10.1, "1+4": 22.8, "2+4": 35.1, "3+4": 26.2, "1+5": 22.0, "2+5": 37.6, "3+5": 42.4, "4+5": 30.2, "1+6": 51.5, "2+6": 26.2, "3+6": 65.5, "4+6": 154.5, "5+6": 173.0, "1+7": 56.9, "2+7": 135.2, "3+7": 94.0, "4+7": 309.0, "5+7": 332.8, "6+7": 254.5}, "exacta": {"1+2": 17.2, "1+3": 3.8, "1+4": 125.7, "1+5": 48.4, "1+6": 277.6, "1+7": 619.2, "2+1": 11.6, "2+3": 21.5, "2+4": 164.2, "2+5": 48.7, "2+6": 111.8, "2+7": 731.8, "3+1": 1.9, "3+2": 25.7, "3+4": 167.7, "3+5": 66.5, "3+6": 236.7, "3+7": 536.7, "4+1": 36.1, "4+2": 59.1, "4+3": 70.0, "4+5": 39.2, "4+6": 447.2, "4+7": 1006.3, "5+1": 67.0, "5+2": 68.2, "5+3": 103.2, "5+4": 88.4, "5+6": 575.0, "5+7": 1006.3, "6+1": 87.5, "6+2": 33.2, "6+3": 93.6, "6+4": 536.7, "6+5": 423.7, "6+7": 731.8, "7+1": 129.8, "7+2": 143.7, "7+3": 89.4, "7+4": 503.1, "7+5": 277.6, "7+6": 536.7}, "win": {}, "anomalies": []}, {"time": "20:47:37", "t": 1784461657.7519777, "minutes_before": 2, "mb_signed": 2, "after_close": false, "baseline_reset": false, "next_race_blocked": false, "quinella": {"1+2": 7.1, "1+3": 1.5, "2+3": 10.7, "1+4": 24.0, "2+4": 38.4, "3+4": 28.7, "1+5": 12.3, "2+5": 22.5, "3+5": 37.3, "4+5": 16.1, "1+6": 56.8, "2+6": 21.6, "3+6": 72.9, "4+6": 162.9, "5+6": 181.0, "1+7": 64.3, "2+7": 152.7, "3+7": 106.2, "4+7": 305.5, "5+7": 376.0, "6+7": 257.2}, "exacta": {"1+2": 16.8, "1+3": 4.1, "1+4": 123.0, "1+5": 25.7, "1+6": 293.7, "1+7": 650.4, "2+1": 12.8, "2+3": 23.6, "2+4": 171.8, "2+5": 34.2, "2+6": 118.2, "2+7": 758.8, "3+1": 2.1, "3+2": 26.8, "3+4": 185.8, "3+5": 51.4, "3+6": 260.1, "3+7": 607.1, "4+1": 34.6, "4+2": 56.9, "4+3": 77.1, "4+5": 19.5, "4+6": 505.9, "4+7": 1011.8, "5+1": 29.0, "5+2": 41.0, "5+3": 105.8, "5+4": 68.9, "5+6": 607.1, "5+7": 1011.8, "6+1": 97.9, "6+2": 28.0, "6+3": 105.8, "6+4": 569.1, "6+5": 433.6, "6+7": 827.8, "7+1": 146.8, "7+2": 135.9, "7+3": 101.1, "7+4": 479.2, "7+5": 275.9, "7+6": 607.1}, "win": {}, "anomalies": ["급락감지: 1+5 -44%", "급락감지: 2+5 -40%", "급락감지: 4+5 -47%"]}, {"time": "20:48:36", "t": 1784461716.8476248, "minutes_before": 1, "mb_signed": 1, "after_close": false, "baseline_reset": false, "next_race_blocked": false, "quinella": {"1+2": 7.4, "1+3": 1.5, "2+3": 11.0, "1+4": 24.9, "2+4": 39.8, "3+4": 29.7, "1+5": 10.5, "2+5": 18.8, "3+5": 33.7, "4+5": 13.5, "1+6": 57.5, "2+6": 22.4, "3+6": 75.5, "4+6": 168.8, "5+6": 187.5, "1+7": 66.6, "2+7": 158.2, "3+7": 110.0, "4+7": 316.5, "5+7": 389.5, "6+7": 266.5}, "exacta": {"1+2": 17.5, "1+3": 4.2, "1+4": 127.2, "1+5": 23.0, "1+6": 293.0, "1+7": 568.8, "2+1": 11.8, "2+3": 24.6, "2+4": 175.8, "2+5": 33.3, "2+6": 122.4, "2+7": 743.8, "3+1": 2.3, "3+2": 27.9, "3+4": 193.3, "3+5": 49.3, "3+6": 235.8, "3+7": 604.3, "4+1": 35.5, "4+2": 54.3, "4+3": 77.9, "4+5": 16.7, "4+6": 402.9, "4+7": 966.9, "5+1": 21.3, "5+2": 35.8, "5+3": 89.5, "5+4": 63.2, "5+6": 604.3, "5+7": 966.9, "6+1": 95.7, "6+2": 29.2, "6+3": 103.9, "6+4": 568.8, "6+5": 371.9, "6+7": 805.8, "7+1": 153.4, "7+2": 140.1, "7+3": 106.2, "7+4": 483.4, "7+5": 276.2, "7+6": 604.3}, "win": {}, "anomalies": []}, {"time": "20:49:37", "t": 1784461777.901838, "minutes_before": 0, "mb_signed": 0, "after_close": false, "baseline_reset": false, "next_race_blocked": false, "quinella": {"1+2": 7.4, "1+3": 1.5, "2+3": 11.0, "1+4": 24.9, "2+4": 39.8, "3+4": 29.7, "1+5": 10.5, "2+5": 18.8, "3+5": 33.7, "4+5": 13.5, "1+6": 57.5, "2+6": 22.4, "3+6": 75.5, "4+6": 168.8, "5+6": 187.5, "1+7": 66.6, "2+7": 158.2, "3+7": 110.0, "4+7": 316.5, "5+7": 389.5, "6+7": 266.5}, "exacta": {"1+2": 17.5, "1+3": 4.2, "1+4": 127.2, "1+5": 23.0, "1+6": 293.0, "1+7": 568.8, "2+1": 11.8, "2+3": 24.6, "2+4": 175.8, "2+5": 33.3, "2+6": 122.4, "2+7": 743.8, "3+1": 2.3, "3+2": 27.9, "3+4": 193.3, "3+5": 49.3, "3+6": 235.8, "3+7": 604.3, "4+1": 35.5, "4+2": 54.3, "4+3": 77.9, "4+5": 16.7, "4+6": 402.9, "4+7": 966.9, "5+1": 21.3, "5+2": 35.8, "5+3": 89.5, "5+4": 63.2, "5+6": 604.3, "5+7": 966.9, "6+1": 95.7, "6+2": 29.2, "6+3": 103.9, "6+4": 568.8, "6+5": 371.9, "6+7": 805.8, "7+1": 153.4, "7+2": 140.1, "7+3": 106.2, "7+4": 483.4, "7+5": 276.2, "7+6": 604.3}, "win": {}, "anomalies": []}, {"time": "20:50:38", "t": 1784461838.0100398, "minutes_before": null, "mb_signed": -1, "after_close": true, "baseline_reset": false, "next_race_blocked": false, "quinella": {"1+2": 7.4, "1+3": 1.5, "2+3": 11.0, "1+4": 24.9, "2+4": 39.8, "3+4": 29.7, "1+5": 10.5, "2+5": 18.8, "3+5": 33.7, "4+5": 13.5, "1+6": 57.5, "2+6": 22.4, "3+6": 75.5, "4+6": 168.8, "5+6": 187.5, "1+7": 66.6, "2+7": 158.2, "3+7": 110.0, "4+7": 316.5, "5+7": 389.5, "6+7": 266.5}, "exacta": {"1+2": 17.5, "1+3": 4.2, "1+4": 127.2, "1+5": 23.0, "1+6": 293.0, "1+7": 568.8, "2+1": 11.8, "2+3": 24.6, "2+4": 175.8, "2+5": 33.3, "2+6": 122.4, "2+7": 743.8, "3+1": 2.3, "3+2": 27.9, "3+4": 193.3, "3+5": 49.3, "3+6": 235.8, "3+7": 604.3, "4+1": 35.5, "4+2": 54.3, "4+3": 77.9, "4+5": 16.7, "4+6": 402.9, "4+7": 966.9, "5+1": 21.3, "5+2": 35.8, "5+3": 89.5, "5+4": 63.2, "5+6": 604.3, "5+7": 966.9, "6+1": 95.7, "6+2": 29.2, "6+3": 103.9, "6+4": 568.8, "6+5": 371.9, "6+7": 805.8, "7+1": 153.4, "7+2": 140.1, "7+3": 106.2, "7+4": 483.4, "7+5": 276.2, "7+6": 604.3}, "win": {}, "anomalies": []}, {"time": "20:51:46", "t": 1784461906.6470385, "minutes_before": null, "mb_signed": -2, "after_close": true, "baseline_reset": false, "next_race_blocked": false, "quinella": {"1+2": 7.4, "1+3": 1.5, "2+3": 11.0, "1+4": 24.9, "2+4": 39.8, "3+4": 29.7, "1+5": 10.5, "2+5": 18.8, "3+5": 33.7, "4+5": 13.5, "1+6": 57.5, "2+6": 22.4, "3+6": 75.5, "4+6": 168.8, "5+6": 187.5, "1+7": 66.6, "2+7": 158.2, "3+7": 110.0, "4+7": 316.5, "5+7": 389.5, "6+7": 266.5}, "exacta": {"1+2": 17.5, "1+3": 4.2, "1+4": 127.2, "1+5": 23.0, "1+6": 293.0, "1+7": 568.8, "2+1": 11.8, "2+3": 24.6, "2+4": 175.8, "2+5": 33.3, "2+6": 122.4, "2+7": 743.8, "3+1": 2.3, "3+2": 27.9, "3+4": 193.3, "3+5": 49.3, "3+6": 235.8, "3+7": 604.3, "4+1": 35.5, "4+2": 54.3, "4+3": 77.9, "4+5": 16.7, "4+6": 402.9, "4+7": 966.9, "5+1": 21.3, "5+2": 35.8, "5+3": 89.5, "5+4": 63.2, "5+6": 604.3, "5+7": 966.9, "6+1": 95.7, "6+2": 29.2, "6+3": 103.9, "6+4": 568.8, "6+5": 371.9, "6+7": 805.8, "7+1": 153.4, "7+2": 140.1, "7+3": 106.2, "7+4": 483.4, "7+5": 276.2, "7+6": 604.3}, "win": {}, "anomalies": []}], "early_drop_horses": {"2": {"firstTime": "20:44:27", "firstMb": 6, "firstPct": -10.0}, "4": {"firstTime": "20:44:27", "firstMb": 6, "firstPct": -10.0}, "6": {"firstTime": "20:44:27", "firstMb": 6, "firstPct": -10.0}}, "analysis": {"keyHorses": [3, 1, 2], "anomalyHorse": 5, "form": [{"no": 1, "name": "岸川 哲也", "jockey": "", "recentPlacings": [], "baseScore": 93.3, "courseBonus": 0, "jockeyBonus": 0, "totalScore": 83.3, "detail": ["빠른페이스·선행 -10", "⚠️ A급 선행마 경합 위험 -5", "선행·안쪽마번 인코스 유리 +5"], "flags": [], "anomaly": null, "bodyWeight": null, "bodyWeightBonus": null, "distAptitude": null, "distAptitudeRate": null, "jockeyRate": null, "jockeyDistRate": null, "competScore": 85.3, "absGrade": "B", "styleType": "선행형", "badTrackRate": null, "jockeyChangeBonus": null, "synergyGrade": null, "synergyRate": null, "trainerName": null, "trainerRate": null, "postPosDelta": null, "grade": "A", "gradeBase": "A", "gait": "선행", "paceBonus": -10, "paceDetail": ["빠른페이스·선행 -10", "⚠️ A급 선행마 경합 위험 -5", "선행·안쪽마번 인코스 유리 +5"]}, {"no": 3, "name": "藤野 一良", "jockey": "", "recentPlacings": [], "baseScore": 84.8, "courseBonus": 0, "jockeyBonus": 0, "totalScore": 104.8, "detail": ["빠른페이스·추입 +15", "💡 A급 추입마 빠른페이스 유리 +10", "추입·안쪽마번 포위 위험 -5"], "flags": [], "anomaly": null, "bodyWeight": null, "bodyWeightBonus": null, "distAptitude": null, "distAptitudeRate": null, "jockeyRate": null, "jockeyDistRate": null, "competScore": 79.8, "absGrade": "C", "styleType": "추입형", "badTrackRate": null, "jockeyChangeBonus": null, "synergyGrade": null, "synergyRate": null, "trainerName": null, "trainerRate": null, "postPosDelta": null, "grade": "A", "gradeBase": "A", "gait": "추입", "paceBonus": 20, "paceDetail": ["빠른페이스·추입 +15", "💡 A급 추입마 빠른페이스 유리 +10", "추입·안쪽마번 포위 위험 -5"]}, {"no": 4, "name": "関 敬", "jockey": "", "recentPlacings": [], "baseScore": 84.0, "courseBonus": 0, "jockeyBonus": 0, "totalScore": 99.0, "detail": ["빠른페이스·추입 +15"], "flags": [], "anomaly": null, "bodyWeight": null, "bodyWeightBonus": null, "distAptitude": null, "distAptitudeRate": null, "jockeyRate": null, "jockeyDistRate": null, "competScore": 79.0, "absGrade": "C", "styleType": "추입형", "badTrackRate": null, "jockeyChangeBonus": null, "synergyGrade": null, "synergyRate": null, "trainerName": null, "trainerRate": null, "postPosDelta": null, "grade": "B", "gradeBase": "B", "gait": "추입", "paceBonus": 15, "paceDetail": ["빠른페이스·추입 +15"]}, {"no": 2, "name": "三浦 大輝", "jockey": "", "recentPlacings": [], "baseScore": 83.1, "courseBonus": 0, "jockeyBonus": 0, "totalScore": 78.1, "detail": ["빠른페이스·선행 -10", "선행·안쪽마번 인코스 유리 +5"], "flags": [], "anomaly": null, "bodyWeight": null, "bodyWeightBonus": null, "distAptitude": null, "distAptitudeRate": null, "jockeyRate": null, "jockeyDistRate": null, "competScore": 80.1, "absGrade": "C", "styleType": "선행형", "badTrackRate": null, "jockeyChangeBonus": null, "synergyGrade": null, "synergyRate": null, "trainerName": null, "trainerRate": null, "postPosDelta": null, "grade": "B", "gradeBase": "B", "gait": "선행", "paceBonus": -5, "paceDetail": ["빠른페이스·선행 -10", "선행·안쪽마번 인코스 유리 +5"]}, {"no": 6, "name": "相良 勝美", "jockey": "", "recentPlacings": [], "baseScore": 73.7, "courseBonus": 0, "jockeyBonus": 0, "totalScore": 88.7, "detail": ["빠른페이스·추입 +15"], "flags": [], "anomaly": null, "bodyWeight": null, "bodyWeightBonus": null, "distAptitude": null, "distAptitudeRate": null, "jockeyRate": null, "jockeyDistRate": null, "competScore": 68.7, "absGrade": "D", "styleType": "추입형", "badTrackRate": null, "jockeyChangeBonus": null, "synergyGrade": null, "synergyRate": null, "trainerName": null, "trainerRate": null, "postPosDelta": null, "grade": "C", "gradeBase": "C", "gait": "추입", "paceBonus": 15, "paceDetail": ["빠른페이스·추입 +15"]}, {"no": 7, "name": "藤田 晃英", "jockey": "", "recentPlacings": [], "baseScore": 72.9, "courseBonus": 0, "jockeyBonus": 0, "totalScore": 87.9, "detail": ["빠른페이스·추입 +15"], "flags": [], "anomaly": null, "bodyWeight": null, "bodyWeightBonus": null, "distAptitude": null, "distAptitudeRate": null, "jockeyRate": null, "jockeyDistRate": null, "competScore": 67.9, "absGrade": "D", "styleType": "추입형", "badTrackRate": null, "jockeyChangeBonus": null, "synergyGrade": null, "synergyRate": null, "trainerName": null, "trainerRate": null, "postPosDelta": null, "grade": "C", "gradeBase": "C", "gait": "추입", "paceBonus": 15, "paceDetail": ["빠른페이스·추입 +15"]}, {"no": 5, "name": "近内 三孝", "jockey": "", "recentPlacings": [], "baseScore": 72.7, "courseBonus": 0, "jockeyBonus": 0, "totalScore": 62.7, "detail": ["빠른페이스·선행 -10"], "flags": [], "anomaly": null, "bodyWeight": null, "bodyWeightBonus": null, "distAptitude": null, "distAptitudeRate": null, "jockeyRate": null, "jockeyDistRate": null, "competScore": 69.7, "absGrade": "D", "styleType": "선행형", "badTrackRate": null, "jockeyChangeBonus": null, "synergyGrade": null, "synergyRate": null, "trainerName": null, "trainerRate": null, "postPosDelta": null, "grade": "D", "gradeBase": "D", "gait": "선행", "paceBonus": -10, "paceDetail": ["빠른페이스·선행 -10"]}], "elimination": {"candidates": [1, 2, 3, 4, 5, 6, 7], "eliminated": [], "horses": [{"no": 1, "name": "岸川 哲也", "oddsRepr": 1.5, "oddsScore": 100, "formScore": 83.3, "formAdj": 20, "total": 120, "avgPlacing": null, "jockeyPlaceRate": null, "favScore": 73.3, "confidence": 30, "marketProb": 50.0, "formProb": 0.0, "combinedProb": 35.0, "ev": -47.5, "verdict": "🟢", "verdictLabel": "유력 후보", "keep": true, "tier": "★", "override": false, "strongCount": 2, "overrideReason": "", "anomalySig": true, "winOdds": null, "highOddsCut": false, "highOddsReason": "", "marketFavorite": true, "formFloored": false, "formScoreAdj": 91.6, "formOddsMult": 1.1, "dualConverge": true, "insuranceDemote": false, "reason": "배당 1.5배 · 쌍승 상위 +20(제거 보류) = 120점", "formGrade": "C"}, {"no": 2, "name": "三浦 大輝", "oddsRepr": 7.4, "oddsScore": 100, "formScore": 78.1, "formAdj": 10, "total": 120, "avgPlacing": null, "jockeyPlaceRate": null, "favScore": 71.2, "confidence": 30, "marketProb": 10.1, "formProb": 0.0, "combinedProb": 7.1, "ev": -47.5, "verdict": "🟢", "verdictLabel": "유력 후보", "keep": true, "tier": "★", "override": false, "strongCount": 2, "overrideReason": "", "anomalySig": true, "winOdds": null, "highOddsCut": false, "highOddsReason": "", "marketFavorite": false, "formFloored": false, "formScoreAdj": 78.1, "formOddsMult": 1.0, "dualConverge": false, "insuranceDemote": false, "reason": "배당 7.4배 · 쌍승 상위 +20(제거 보류) = 120점", "formGrade": "C"}, {"no": 3, "name": "藤野 一良", "oddsRepr": 1.5, "oddsScore": 100, "formScore": 104.8, "formAdj": 20, "total": 120, "avgPlacing": null, "jockeyPlaceRate": null, "favScore": 81.9, "confidence": 30, "marketProb": 50.0, "formProb": 0.0, "combinedProb": 35.0, "ev": -47.5, "verdict": "🟢", "verdictLabel": "유력 후보", "keep": true, "tier": "★", "override": false, "strongCount": 2, "overrideReason": "", "anomalySig": true, "winOdds": null, "highOddsCut": false, "highOddsReason": "", "marketFavorite": true, "formFloored": false, "formScoreAdj": 100.0, "formOddsMult": 1.1, "dualConverge": true, "insuranceDemote": false, "reason": "배당 1.5배 · 쌍승 상위 +20(제거 보류) = 120점", "formGrade": "A"}, {"no": 4, "name": "関 敬", "oddsRepr": 13.5, "oddsScore": 100, "formScore": 99.0, "formAdj": 20, "total": 120, "avgPlacing": null, "jockeyPlaceRate": null, "favScore": 79.6, "confidence": 30, "marketProb": 5.6, "formProb": 0.0, "combinedProb": 3.9, "ev": -47.5, "verdict": "🟢", "verdictLabel": "유력 후보", "keep": true, "tier": "★", "override": false, "strongCount": 2, "overrideReason": "", "anomalySig": true, "winOdds": null, "highOddsCut": false, "highOddsReason": "", "marketFavorite": false, "formFloored": false, "formScoreAdj": 69.3, "formOddsMult": 0.7, "dualConverge": false, "insuranceDemote": false, "reason": "배당 13.5배 · 쌍승 상위 +20(제거 보류) = 120점", "formGrade": "A"}, {"no": 5, "name": "近内 三孝", "oddsRepr": 10.5, "oddsScore": 100, "formScore": 62.7, "formAdj": 10, "total": 120, "avgPlacing": null, "jockeyPlaceRate": null, "favScore": 65.1, "confidence": 30, "marketProb": 7.1, "formProb": 0.0, "combinedProb": 5.0, "ev": -47.5, "verdict": "🟢", "verdictLabel": "유력 후보", "keep": true, "tier": "★", "override": false, "strongCount": 2, "overrideReason": "", "anomalySig": true, "winOdds": null, "highOddsCut": false, "highOddsReason": "", "marketFavorite": false, "formFloored": false, "formScoreAdj": 43.9, "formOddsMult": 0.7, "dualConverge": false, "insuranceDemote": false, "reason": "배당 10.5배 · 쌍승 상위 +20(제거 보류) = 120점", "formGrade": "D"}, {"no": 6, "name": "相良 勝美", "oddsRepr": 22.4, "oddsScore": 100, "formScore": 88.7, "formAdj": 20, "total": 120, "avgPlacing": null, "jockeyPlaceRate": null, "favScore": 75.5, "confidence": 30, "marketProb": 3.3, "formProb": 0.0, "combinedProb": 2.3, "ev": -47.5, "verdict": "🟢", "verdictLabel": "유력 후보", "keep": true, "tier": "★", "override": false, "strongCount": 2, "overrideReason": "", "anomalySig": true, "winOdds": null, "highOddsCut": false, "highOddsReason": "", "marketFavorite": false, "formFloored": false, "formScoreAdj": 62.1, "formOddsMult": 0.7, "dualConverge": false, "insuranceDemote": true, "reason": "배당 22.4배 · 쌍승 상위 +20(제거 보류) = 120점", "formGrade": "B"}, {"no": 7, "name": "藤田 晃英", "oddsRepr": 66.6, "oddsScore": 40, "formScore": 87.9, "formAdj": 20, "total": 100, "avgPlacing": null, "jockeyPlaceRate": null, "favScore": 60.2, "confidence": 0, "marketProb": 1.1, "formProb": 0.0, "combinedProb": 0.8, "ev": -47.5, "verdict": "🟢", "verdictLabel": "유력 후보", "keep": true, "tier": "△", "override": false, "strongCount": 1, "overrideReason": "", "anomalySig": false, "winOdds": null, "highOddsCut": false, "highOddsReason": "", "marketFavorite": false, "formFloored": false, "formScoreAdj": 61.5, "formOddsMult": 0.7, "dualConverge": false, "insuranceDemote": true, "reason": "배당 66.6배 · 감점 없음 = 100점", "formGrade": "B"}], "counts": {"entrants": 7, "candidates": 7, "eliminated": 0}}, "signals": ["1+5 복승 12.3→10.5 (2분전 대비 -14.6%)", "2+5 복승 22.5→18.8 (2분전 대비 -16.4%)", "4+5 복승 16.1→13.5 (2분전 대비 -16.1%)", "3+5 복승 40.2→33.7 (5분전 대비 -16.2%)", "2+6 복승 30.5→22.4 (5분전 대비 -26.6%)", "🔄 역전감지: 단승 1번 유력이나 쌍승에서 4번 1착(35.5)이 1번 1착(127.2)보다 낮음 → 실질 1착: 4번 가능성 (압도적 역배열 0.279)", "🔄 역전감지: 단승 1번 유력이나 쌍승에서 6번 1착(95.7)이 1번 1착(293.0)보다 낮음 → 실질 1착: 6번 가능성 (압도적 역배열 0.327)", "🔄 역전감지: 단승 1번 유력이나 쌍승에서 3번 1착(2.3)이 1번 1착(4.2)보다 낮음 → 실질 1착: 3번 가능성 (강한 역배열 0.548)", "🔄 역전감지: 단승 1번 유력이나 쌍승에서 2번 1착(11.8)이 1번 1착(17.5)보다 낮음 → 실질 1착: 2번 가능성 (역배열 0.674)"], "signalsDetail": [{"level": "🔴", "type": "마감급락", "combo": [1, 5], "text": "1+5 복승 12.3→10.5 (2분전 대비 -14.6%)", "detail": "마감 2분전 대비 급락 → 마감 임박 확정성 높음", "oddsBefore": 12.3, "oddsAfter": 10.5, "dropPct": -14.6, "highOdds": false, "minutesBefore": -1, "phase": "마감 후", "afterClose": true, "note": "⚠️ 마감 후 신호 - 참고만(추천 미반영)"}, {"level": "🔴", "type": "마감급락", "combo": [2, 5], "text": "2+5 복승 22.5→18.8 (2분전 대비 -16.4%)", "detail": "마감 2분전 대비 급락 → 마감 임박 확정성 높음", "oddsBefore": 22.5, "oddsAfter": 18.8, "dropPct": -16.4, "highOdds": false, "minutesBefore": -1, "phase": "마감 후", "afterClose": true, "note": "⚠️ 마감 후 신호 - 참고만(추천 미반영)"}, {"level": "🔴", "type": "마감급락", "combo": [4, 5], "text": "4+5 복승 16.1→13.5 (2분전 대비 -16.1%)", "detail": "마감 2분전 대비 급락 → 마감 임박 확정성 높음", "oddsBefore": 16.1, "oddsAfter": 13.5, "dropPct": -16.1, "highOdds": false, "minutesBefore": -1, "phase": "마감 후", "afterClose": true, "note": "⚠️ 마감 후 신호 - 참고만(추천 미반영)"}, {"level": "🟠", "type": "마감급락", "combo": [3, 5], "text": "3+5 복승 40.2→33.7 (5분전 대비 -16.2%)", "detail": "마감 5분전 대비 급락 → 자금 유입 가속(주목)", "oddsBefore": 40.2, "oddsAfter": 33.7, "dropPct": -16.2, "highOdds": false, "minutesBefore": -1, "phase": "마감 후", "afterClose": true, "note": "⚠️ 마감 후 신호 - 참고만(추천 미반영)"}, {"level": "🟠", "type": "마감급락", "combo": [2, 6], "text": "2+6 복승 30.5→22.4 (5분전 대비 -26.6%)", "detail": "마감 5분전 대비 급락 → 자금 유입 가속(주목)", "oddsBefore": 30.5, "oddsAfter": 22.4, "dropPct": -26.6, "highOdds": false, "minutesBefore": -1, "phase": "마감 후", "afterClose": true, "note": "⚠️ 마감 후 신호 - 참고만(추천 미반영)"}, {"level": "🔴🔴", "type": "쌍승역전공식", "horse": 4, "text": "🔄 역전감지: 단승 1번 유력이나 쌍승에서 4번 1착(35.5)이 1번 1착(127.2)보다 낮음 → 실질 1착: 4번 가능성 (압도적 역배열 0.279)", "detail": "역전비율 = 쌍승(4→1) 35.5 / 쌍승(1→4) 127.2 = 0.279 (압도적 역배열)", "minutesBefore": -1, "phase": "마감 후", "afterClose": true, "note": "⚠️ 마감 후 신호 - 참고만(추천 미반영)"}, {"level": "🔴🔴", "type": "쌍승역전공식", "horse": 6, "text": "🔄 역전감지: 단승 1번 유력이나 쌍승에서 6번 1착(95.7)이 1번 1착(293.0)보다 낮음 → 실질 1착: 6번 가능성 (압도적 역배열 0.327)", "detail": "역전비율 = 쌍승(6→1) 95.7 / 쌍승(1→6) 293.0 = 0.327 (압도적 역배열)", "minutesBefore": -1, "phase": "마감 후", "afterClose": true, "note": "⚠️ 마감 후 신호 - 참고만(추천 미반영)"}, {"level": "🔴", "type": "쌍승역전공식", "horse": 3, "text": "🔄 역전감지: 단승 1번 유력이나 쌍승에서 3번 1착(2.3)이 1번 1착(4.2)보다 낮음 → 실질 1착: 3번 가능성 (강한 역배열 0.548)", "detail": "역전비율 = 쌍승(3→1) 2.3 / 쌍승(1→3) 4.2 = 0.548 (강한 역배열)", "minutesBefore": -1, "phase": "마감 후", "afterClose": true, "note": "⚠️ 마감 후 신호 - 참고만(추천 미반영)"}, {"level": "🟠", "type": "쌍승역전공식", "horse": 2, "text": "🔄 역전감지: 단승 1번 유력이나 쌍승에서 2번 1착(11.8)이 1번 1착(17.5)보다 낮음 → 실질 1착: 2번 가능성 (역배열 0.674)", "detail": "역전비율 = 쌍승(2→1) 11.8 / 쌍승(1→2) 17.5 = 0.674 (역배열)", "minutesBefore": -1, "phase": "마감 후", "afterClose": true, "note": "⚠️ 마감 후 신호 - 참고만(추천 미반영)"}], "betRecommend": [{"kind": "복승", "label": "복승 메인", "combo": [1, 3], "alloc": 62.1, "expOdds": 1.5, "signalQuality": "하", "signalReason": "집중 급락 없음(시장 전체 급락·노이즈)"}, {"kind": "복승", "label": "복승 보조(삼복승 구성)", "combo": [1, 2], "alloc": 20, "expOdds": 7.4, "signalQuality": "하", "signalReason": "집중 급락 없음(시장 전체 급락·노이즈)"}, {"kind": "복승", "label": "복승 보조(삼복승 구성)", "combo": [2, 3], "alloc": 12, "expOdds": 11.0, "signalQuality": "하", "signalReason": "집중 급락 없음(시장 전체 급락·노이즈)"}, {"kind": "삼복승", "label": "삼복승 메인", "combo": [1, 2, 3], "alloc": 14.1, "expOdds": null, "expOddsEst": 9.9, "reversalPick": true, "signalQuality": "하", "signalReason": "집중 급락 없음(시장 전체 급락·노이즈)", "estimated": true}, {"kind": "삼복승", "label": "삼복승 보험1", "combo": [1, 3, 5], "alloc": 1.9, "expOdds": null, "expOddsEst": 16.2, "reversalPick": true, "signalQuality": "하", "signalReason": "집중 급락 없음(시장 전체 급락·노이즈)", "estimated": true}, {"kind": "삼복승", "label": "삼복승 보험2", "combo": [2, 3, 5], "alloc": 1.9, "expOdds": null, "expOddsEst": 38.2, "reversalPick": true, "signalQuality": "하", "signalReason": "집중 급락 없음(시장 전체 급락·노이즈)", "estimated": true}], "final_recommend": {"quinella_main": "1+3", "quinella_sub": null, "trifecta_main": "1+2+3"}, "summary": "유력마 3·1·2 / 복승 1+3", "at": 1784461801.3335414}, "closing_drop_horses": {"4": {"firstTime": "20:47:37", "firstMb": 2, "firstPct": -47.0}, "1": {"firstTime": "20:47:37", "firstMb": 2, "firstPct": -44.0}, "5": {"firstTime": "20:47:37", "firstMb": 2, "firstPct": -35.8}, "2": {"firstTime": "20:47:37", "firstMb": 2, "firstPct": -29.0}}}